OWNd/__init__.py
OWNd/__main__.py
OWNd/connection.py
OWNd/discovery.py
OWNd/message.py
OWNd-0.7.49.dist-info/LICENSE
OWNd-0.7.49.dist-info/METADATA
OWNd-0.7.49.dist-info/WHEEL
OWNd-0.7.49.dist-info/top_level.txt
OWNd-0.7.49.dist-info/RECORD
