Metadata-Version: 2.2
Name: OWNd
Version: 0.7.49
Summary: Python interface for the OpenWebNet protocol
Home-page: https://github.com/anotherjulien/OWNd
Author: anotherjulien
Author-email: yetanotherjulien@gmail.com
Classifier: Programming Language :: Python :: 3.8
Classifier: License :: OSI Approved :: GNU General Public License v3 (GPLv3)
Classifier: Operating System :: OS Independent
Requires-Python: >=3.8
License-File: LICENSE
Requires-Dist: aiohttp
Requires-Dist: pytz
Requires-Dist: python-dateutil
Dynamic: author
Dynamic: author-email
Dynamic: classifier
Dynamic: description
Dynamic: description-content-type
Dynamic: home-page
Dynamic: requires-dist
Dynamic: requires-python
Dynamic: summary
